simplebot_deltaland/__init__.py
simplebot_deltaland/_version.py
simplebot_deltaland/consts.py
simplebot_deltaland/cooldown.py
simplebot_deltaland/dice.py
simplebot_deltaland/experience.py
simplebot_deltaland/game.py
simplebot_deltaland/migrations.py
simplebot_deltaland/orm.py
simplebot_deltaland/quests.py
simplebot_deltaland/util.py
simplebot_deltaland/images/LICENSE.txt
simplebot_deltaland/images/castle.webp
simplebot_deltaland/images/cauldron.webp
simplebot_deltaland/images/goblin.webp
simplebot_deltaland/images/level-up.webp
simplebot_deltaland/images/tavern.webp
simplebot_deltaland-0.1.0.dist-info/LICENSE
simplebot_deltaland-0.1.0.dist-info/METADATA
simplebot_deltaland-0.1.0.dist-info/WHEEL
simplebot_deltaland-0.1.0.dist-info/entry_points.txt
simplebot_deltaland-0.1.0.dist-info/top_level.txt
simplebot_deltaland-0.1.0.dist-info/RECORD
