Metadata-Version: 2.1
Name: simplebot-deltaland
Version: 0.1.0
Summary: Fantasy game for Delta Chat (SimpleBot plugin)
Home-page: https://github.com/adbenitez/simplebot_deltaland
Author: adbenitez
Author-email: adbenitez@nauta.cu
License: GPLv3
Keywords: simplebot plugin deltachat game
Classifier: Development Status :: 4 - Beta
Classifier: Environment :: Plugins
Classifier: Programming Language :: Python :: 3
Classifier: License :: OSI Approved :: GNU General Public License v3 (GPLv3)
Classifier: Operating System :: OS Independent
Classifier: Topic :: Utilities
License-File: LICENSE
Requires-Dist: simplebot (>=4.1.0)
Requires-Dist: SQLAlchemy (>=1.4.42)
Provides-Extra: dev
Requires-Dist: simplebot (>=4.1.0) ; extra == 'dev'
Requires-Dist: SQLAlchemy (>=1.4.42) ; extra == 'dev'
Requires-Dist: pytest (>=7.2.0) ; extra == 'dev'
Requires-Dist: black (>=22.10.0) ; extra == 'dev'
Requires-Dist: mypy (>=0.982) ; extra == 'dev'
Requires-Dist: isort (>=5.10.1) ; extra == 'dev'
Requires-Dist: pylint (>=2.12.2) ; extra == 'dev'
Requires-Dist: pylama (>=8.4.1) ; extra == 'dev'
Provides-Extra: test
Requires-Dist: pytest (>=7.2.0) ; extra == 'test'
